setup.py
ymsg/__init__.py
ymsg/const.py
ymsg/packet.py
ymsg/session.py
ymsg/util.py
ymsglib.egg-info/PKG-INFO
ymsglib.egg-info/SOURCES.txt
ymsglib.egg-info/dependency_links.txt
ymsglib.egg-info/top_level.txt