Metadata-Version: 1.0
Name: ymsglib
Version: 0.1
Summary: Module implementing the yahoo messenger protocol v16.
Home-page: http://code.google.com/p/ymsg/
Author: Daniel Anechitoaie
Author-email: daniel dot anechitoaie at gmail dot com
License: UNKNOWN
Platform: UNKNOWN
Classifier: Development Status :: 2 - Pre-Alpha
Classifier: Intended Audience :: Developers
Classifier: License :: OSI Approved :: GNU General Public License (GPL)
Classifier: Operating System :: Microsoft :: Windows
Classifier: Operating System :: POSIX
Classifier: Programming Language :: Python
Classifier: Topic :: System :: Networking
